LICENSE.txt
README.md
setup.cfg
setup.py
src/SubStrat/SubStrat.py
src/SubStrat/__init__.py
src/SubStrat/automl_wrappers/__init__.py
src/SubStrat/automl_wrappers/base_automl_wrapper.py
src/SubStrat/automl_wrappers/sklean_wrapper.py
src/SubStrat/genetic_sub_algorithm/__init__.py
src/SubStrat/genetic_sub_algorithm/gene.py
src/SubStrat/genetic_sub_algorithm/population.py
src/SubStrat/genetic_sub_algorithm/population_initialization.py
src/SubStrat/genetic_sub_algorithm/selection.py
src/SubStrat/sub_algo_utils/__init__.py
src/SubStrat/sub_algo_utils/fitness.py
src/SubStrat/sub_algo_utils/prepare_data.py
src/SubStrat/sub_algo_utils/sub_dataset_size.py
src/SubStrat/summary_algorithm/__init__.py
src/SubStrat/summary_algorithm/basic_summary_algorithm.py
src/SubStrat/summary_algorithm/genetic_sub_algorithm.py
src/substrat_automl.egg-info/PKG-INFO
src/substrat_automl.egg-info/SOURCES.txt
src/substrat_automl.egg-info/dependency_links.txt
src/substrat_automl.egg-info/requires.txt
src/substrat_automl.egg-info/top_level.txt
test/test_init_population.py
test/test_population.py