Metadata-Version: 2.1
Name: substrat-automl
Version: 0.4
Summary: A Python package for automated machine learning tasks with genetic algorithm-based dataset summarization.
Home-page: https://github.com/analysis-bots/SubStrat
Author: Eyal Elboim
Author-email: Eyal.Elboim1@gmail.com
License: UNKNOWN
Platform: UNKNOWN
Requires-Python: >=3.8
License-File: LICENSE.txt
